evc_manager/__init__.py
evc_manager/__main__.py
evc_manager/backends/__init__.py
evc_manager/backends/generic_backend.py
evc_manager/backends/kytos_eline.py
evc_manager/backends/oess.py
evc_manager/docs/add_example_evc_range.yaml
evc_manager/docs/evc_example_to_add.yaml
evc_manager/docs/evc_modeling/evc_definition.yaml
evc_manager/docs/evc_modeling/evc_example_list_of_evcs.yaml
evc_manager/docs/evc_modeling/evc_example_request_to_add.yaml
evc_manager/docs/evc_modeling/evc_example_request_to_delete.yaml
evc_manager/docs/evc_remove.yaml
evc_manager/docs/objects_definition.txt
evc_manager/evc_manager.py
evc_manager/libs/__init__.py
evc_manager/libs/core/__init__.py
evc_manager/libs/core/cli.py
evc_manager/libs/core/create_template_files.py
evc_manager/libs/core/evc_list.py
evc_manager/libs/core/evc_to_dict.py
evc_manager/libs/core/fix_variables.py
evc_manager/libs/core/import_evc.py
evc_manager/libs/core/log.py
evc_manager/libs/core/parse_add_range_evcs.py
evc_manager/libs/core/prep_cli.py
evc_manager/libs/core/read_file.py
evc_manager/libs/core/shortcut_file.py
evc_manager/libs/core/singleton.py
evc_manager/libs/models/__init__.py
evc_manager/libs/models/current_config.py
evc_manager/libs/models/evc.py
evc_manager/libs/models/evc_paths.py
evc_manager/libs/models/mac_address.py
evc_manager/libs/models/mac_addresses.py
evc_manager/libs/models/metrics.py
evc_manager/libs/models/monitoring.py
evc_manager/libs/models/nni.py
evc_manager/libs/models/notifications.py
evc_manager/libs/models/tag.py
evc_manager/libs/models/uni.py
evc_manager/libs/models/unis.py
evc_manager/libs/outputs/__init__.py
evc_manager/libs/outputs/printing.py
evc_manager/libs/outputs/to_json.py
evc_manager/libs/outputs/to_screen.py
evc_manager/libs/outputs/to_stats.py
evc_manager/libs/outputs/to_table.py
evc_manager/libs/outputs/to_yaml.py
evc_manager-1.3.15.dist-info/METADATA
evc_manager-1.3.15.dist-info/WHEEL
evc_manager-1.3.15.dist-info/RECORD
